app/__init__.py
scoring_python_test-0.3.0.dist-info/DESCRIPTION.rst
scoring_python_test-0.3.0.dist-info/METADATA
scoring_python_test-0.3.0.dist-info/RECORD
scoring_python_test-0.3.0.dist-info/WHEEL
scoring_python_test-0.3.0.dist-info/metadata.json
scoring_python_test-0.3.0.dist-info/top_level.txt
