Metadata-Version: 2.0
Name: scoring-python-test
Version: 0.3.0
Summary: UNKNOWN
Home-page: https://gitlab.worldline.tech/david.chaille/python_test_deployment
Author: David Chaille
Author-email: davidchaille94@gmail.com
License: UNKNOWN
Platform: UNKNOWN
Requires-Dist: flask
